setup.py
install_composer/__init__.py
install_composer.egg-info/PKG-INFO
install_composer.egg-info/SOURCES.txt
install_composer.egg-info/dependency_links.txt
install_composer.egg-info/not-zip-safe
install_composer.egg-info/top_level.txt