Metadata-Version: 1.0
Name: install-composer
Version: 0.1
Summary: install composer
Home-page: https://github.com/haradashinya/install_composer
Author: haradashinya
Author-email: haradashinya@gmail.com
License: MIT
Platform: UNKNOWN
